README.rst
setup.py
gbgb/__init__.py
gbgb/utils.py
gbgb.egg-info/PKG-INFO
gbgb.egg-info/SOURCES.txt
gbgb.egg-info/dependency_links.txt
gbgb.egg-info/requires.txt
gbgb.egg-info/top_level.txt
gbgb/maps/__init__.py
gbgb/maps/features.py
gbgb/maps/qualifiers.py