Metadata-Version: 1.1
Name: gbgb
Version: 0.1.0
Summary: Goodbye, GenBank is a package for use with Biopython that gives feature annotations from GenBank records a new and better life.
Home-page: https://github.com/biosustain/goodbye-genbank
Author: Lars Schöning
Author-email: lays@biosustain.dtu.dk
License: Apache
Platform: UNKNOWN
Classifier: Development Status :: 4 - Beta
Classifier: Environment :: Console
Classifier: Intended Audience :: Developers
Classifier: Intended Audience :: Science/Research
Classifier: License :: OSI Approved :: Apache Software License
Classifier: Operating System :: OS Independent
Classifier: Programming Language :: Python
Classifier: Programming Language :: Python :: 2.7
Classifier: Programming Language :: Python :: 3
Classifier: Programming Language :: Python :: 3.3
Classifier: Programming Language :: Python :: 3.4
Classifier: Programming Language :: Python :: 3.5
Classifier: Topic :: Scientific/Engineering
Classifier: Topic :: Scientific/Engineering :: Bio-Informatics
